data_forager/__init__.py
data_forager/sample_index.py
data_forager/unzip_files.py
data_forager/utils.py
data_forager/datasets/__init__.py
data_forager/datasets/common.py
data_forager/datasets/jsonl.py
data_forager/datasets/tokens.py
data_forager/index_stores/__init__.py
data_forager/index_stores/common.py
data_forager/index_stores/fs_based.py
data_forager/indexers/__init__.py
data_forager/indexers/jsonl_indexer.py
data_forager/indexers/text_lines.py
data_forager/indexers/tokenization_indexer.py
data_forager-0.1.6.dist-info/licenses/LICENSE
data_forager-0.1.6.dist-info/METADATA
data_forager-0.1.6.dist-info/WHEEL
data_forager-0.1.6.dist-info/top_level.txt
data_forager-0.1.6.dist-info/RECORD
