Metadata-Version: 2.4
Name: data-forager
Version: 0.1.6
Summary: Enabling random access to large datasets on disk for PyTorch training and other use cases
Author-email: Freddy Snijder <forager@visionscapers.com>
License-Expression: MIT
Project-URL: Homepage, https://github.com/visionscaper/data-forager
Project-URL: Repository, https://github.com/visionscaper/data-forager
Project-URL: Issues, https://github.com/visionscaper/data-forager/issues
Keywords: machine-learning,deep-learning,pytorch,dataset,dataloader,random-access,large-scale,training
Classifier: Development Status :: 4 - Beta
Classifier: Intended Audience :: Developers
Classifier: Intended Audience :: Science/Research
Classifier: Operating System :: OS Independent
Classifier: Programming Language :: Python :: 3
Classifier: Programming Language :: Python :: 3.9
Classifier: Programming Language :: Python :: 3.10
Classifier: Programming Language :: Python :: 3.11
Classifier: Programming Language :: Python :: 3.12
Classifier: Topic :: Scientific/Engineering :: Artificial Intelligence
Requires-Python: >=3.9
License-File: LICENSE
Requires-Dist: numpy
Requires-Dist: tqdm
Requires-Dist: natsort
Requires-Dist: visionscaper-pybase
Provides-Extra: dev
Requires-Dist: pytest; extra == "dev"
Requires-Dist: tiktoken; extra == "dev"
Requires-Dist: build; extra == "dev"
Requires-Dist: twine; extra == "dev"
Dynamic: license-file
